{"ts":"2023-12-23T07:15:05.257Z","level":"error","error":{"originalError":{"name":"AccessTokenInvalid","message":"{\n  \"status\": 401,\n  \"statusText\": \"Unauthorized\",\n  \"message\": \"The access token you sent could not be found or is invalid.\",\n  \"details\": {},\n  \"request\": {\n    \"url\": \"/spaces/xz5qx1qjh5v3\",\n    \"headers\": {\n      \"Accept\": \"application/json, text/plain, */*\",\n      \"Content-Type\": \"application/vnd.contentful.management.v1+json\",\n      \"X-Contentful-User-Agent\": \"app contentful.import/8.5.63; feature library-import; sdk contentful-management.js/0.0.0-determined-by-semantic-release; platform node.js/v20.5.1; os macOS/v20.5.1;\",\n      \"CF-Sequence\": \"4dcb8451-2614-4692-a816-5a9eeabe29b3\",\n      \"Authorization\": \"Bearer ...rer v\",\n      \"User-Agent\": \"axios/1.5.1\",\n      \"Accept-Encoding\": \"gzip, compress, deflate, br\"\n    },\n    \"method\": \"get\"\n  },\n  \"requestId\": \"4d13813e-4095-48fa-960d-2ee581de4ee2\"\n}"},"data":{"status":401,"statusText":"Unauthorized","message":"The access token you sent could not be found or is invalid.","details":{},"request":{"url":"/spaces/xz5qx1qjh5v3","headers":{"Accept":"application/json, text/plain, */*","Content-Type":"application/vnd.contentful.management.v1+json","X-Contentful-User-Agent":"app contentful.import/8.5.63; feature library-import; sdk contentful-management.js/0.0.0-determined-by-semantic-release; platform node.js/v20.5.1; os macOS/v20.5.1;","CF-Sequence":"4dcb8451-2614-4692-a816-5a9eeabe29b3","Authorization":"Bearer ...rer v","User-Agent":"axios/1.5.1","Accept-Encoding":"gzip, compress, deflate, br"},"method":"get"},"requestId":"4d13813e-4095-48fa-960d-2ee581de4ee2"}}}